shellvars/__init__.py
shellvars/tests/__init__.py
shellvars/tests/test_shellvars.py
shellvars-1.0.0.dist-info/metadata.json
shellvars-1.0.0.dist-info/DESCRIPTION.rst
shellvars-1.0.0.dist-info/RECORD
shellvars-1.0.0.dist-info/top_level.txt
shellvars-1.0.0.dist-info/WHEEL
shellvars-1.0.0.dist-info/METADATA
shellvars-1.0.0.dist-info/pbr.json
