Metadata-Version: 2.0
Name: shellvars
Version: 1.0.0
Summary: Evaluator for common shell variable expressions
Home-page: https://github.com/testing-cabal/shellvars
Author: Robert Collins
Author-email: robertc@robertcollins.net
License: UNKNOWN
Platform: UNKNOWN
Classifier: License :: OSI Approved :: MIT License
Classifier: Programming Language :: Python :: 2
Classifier: Programming Language :: Python :: 3
Requires-Dist: parsley
Provides-Extra: test
Requires-Dist: docutils; extra == 'test'
Requires-Dist: testscenarios; extra == 'test'
Requires-Dist: testtools; extra == 'test'
Provides-Extra: test
Requires-Dist: hypothesis; (python_version!='3.2') and extra == 'test'
